prometheus_metrics_proto/__init__.py
prometheus_metrics_proto/api.py
prometheus_metrics_proto/prometheus_metrics_pb2.py
prometheus_metrics_proto/utils.py
prometheus_metrics_proto-18.1.2.dist-info/LICENSE
prometheus_metrics_proto-18.1.2.dist-info/METADATA
prometheus_metrics_proto-18.1.2.dist-info/WHEEL
prometheus_metrics_proto-18.1.2.dist-info/top_level.txt
prometheus_metrics_proto-18.1.2.dist-info/RECORD
