Metadata-Version: 2.1
Name: prometheus-metrics-proto
Version: 18.1.2
Summary: Prometheus binary format metrics data structures for Python client libraries
Home-page: https://github.com/claws/prometheus_metrics_proto
Author: Chris Laws
Author-email: clawsicus@gmail.com
License: MIT
Keywords: prometheus,monitoring,metrics
Platform: UNKNOWN
Classifier: Intended Audience :: Developers
Classifier: License :: OSI Approved :: MIT License
Classifier: Operating System :: OS Independent
Classifier: Programming Language :: Python :: 3.6
Classifier: Programming Language :: Python :: 3.7
Classifier: Programming Language :: Python :: 3.8
Classifier: Topic :: System :: Monitoring
Requires-Dist: protobuf
